novaposhta/__init__.py
novaposhta/chains.py
novaposhta/client.py
novaposhta/models/__init__.py
novaposhta/models/additional_service.py
novaposhta/models/address.py
novaposhta/models/base.py
novaposhta/models/common.py
novaposhta/models/contact_person.py
novaposhta/models/counterparty.py
novaposhta/models/internet_document.py
novaposhta/models/scan_sheet.py
novaposhta/models/tracking_document.py
novaposhta/mypi.ini
novaposhta/types.py
novaposhta_python_client-0.1.12.dist-info/METADATA
novaposhta_python_client-0.1.12.dist-info/WHEEL
novaposhta_python_client-0.1.12.dist-info/licenses/LICENSE.md
novaposhta_python_client-0.1.12.dist-info/RECORD
