Metadata-Version: 2.4
Name: novaposhta-python-client
Version: 0.1.12
Summary: Python client for Nova Poshta API
License: MIT
License-File: LICENSE.md
Keywords: api,nova-poshta,novaposhta,nova-poshta-api,novaposhta-api
Author: Oleksii
Author-email: semolex@live.com
Requires-Python: >=3.9,<4.0
Classifier: Development Status :: 5 - Production/Stable
Classifier: Intended Audience :: Developers
Classifier: License :: OSI Approved :: MIT License
Classifier: Natural Language :: English
Classifier: Operating System :: OS Independent
Classifier: Programming Language :: Python :: 3
Classifier: Programming Language :: Python :: 3.9
Classifier: Programming Language :: Python :: 3.10
Classifier: Programming Language :: Python :: 3.11
Classifier: Programming Language :: Python :: 3.12
Classifier: Programming Language :: Python :: 3.13
Classifier: Programming Language :: Python :: 3.14
Classifier: Programming Language :: Python :: 3 :: Only
Classifier: Programming Language :: Python :: Implementation :: CPython
Classifier: Topic :: Software Development :: Build Tools
Classifier: Topic :: Software Development :: Libraries :: Python Modules
Classifier: Typing :: Typed
Requires-Dist: h11 (>=0.16.0,<0.17.0)
Requires-Dist: httpx (>=0.24.0)
Project-URL: Homepage, https://github.com/semolex/novaposhta-python-client
Project-URL: Repository, https://github.com/semolex/novaposhta-python-client
